enlil.py
pipeline/__init__.py
pipeline/decoder/__init__.py
pipeline/decoder/decoder.py
pipeline/loader/__init__.py
pipeline/loader/entity_loader.py
pipeline/loader/entities/__init__.py
pipeline/loader/entities/area.py
pipeline/loader/entities/image.py
pipeline/loader/entities/package.py
pipeline/loader/entities/robot.py
pipeline/renderizer/__init__.py
pipeline/renderizer/renderizer.py
pipeline/renderizer/templates/docker_compose.j2
pipeline/renderizer/templates/dockerfile.j2
enlil-1.1.3.dist-info/LICENSE
enlil-1.1.3.dist-info/METADATA
enlil-1.1.3.dist-info/WHEEL
enlil-1.1.3.dist-info/entry_points.txt
enlil-1.1.3.dist-info/top_level.txt
enlil-1.1.3.dist-info/RECORD
