Metadata-Version: 2.1
Name: enlil
Version: 1.1.3
Summary: Automatic containerization of complete ROS workspaces.
Home-page: https://github.com/MisterOwlPT/enlil
Author: Pedro Melo, Rafael Arrais
Author-email: pedro.m.melo@inesctec.pt, rafael.l.arrais@inesctec.pt
License: MIT
Platform: UNKNOWN
Classifier: Environment :: Console
Classifier: Intended Audience :: Developers
Classifier: License :: OSI Approved :: MIT License
Classifier: Operating System :: MacOS :: MacOS X
Classifier: Operating System :: Microsoft :: Windows
Classifier: Operating System :: POSIX
Classifier: Programming Language :: Python :: 3
Classifier: Programming Language :: Python :: 3.6
Classifier: Programming Language :: Python :: 3.7
Classifier: Programming Language :: Python :: 3.8
Classifier: Programming Language :: Python :: 3.9
Requires-Python: >=3.6
Requires-Dist: docopt
Requires-Dist: jinja2
Requires-Dist: pyyaml
